{
  "$schema": "https://ui.shadcn.com/schema/registry-item.json",
  "name": "badge",
  "title": "Badge",
  "description": "Status pill / label, tinted-bg variants. useRender hook for polymorphism (no Base UI primitive needed — badges aren't interactive).",
  "dependencies": [
    "@base-ui/react",
    "class-variance-authority"
  ],
  "registryDependencies": [
    "theme",
    "utils"
  ],
  "files": [
    {
      "path": "registry/hola/ui/badge.tsx",
      "content": "import { mergeProps } from \"@base-ui/react/merge-props\";\nimport { useRender } from \"@base-ui/react/use-render\";\nimport { cva, type VariantProps } from \"class-variance-authority\";\n\nimport { cn } from \"@/registry/hola/lib/utils\";\n\nconst badgeVariants = cva(\n  cn(\n    \"inline-flex w-fit shrink-0 items-center justify-center gap-1 overflow-hidden whitespace-nowrap\",\n    \"h-5 px-2 py-0.5 rounded-full\",\n    \"text-xs font-medium\",\n    \"border border-transparent bg-clip-padding\",\n    \"focus-visible:outline-2 focus-visible:outline-offset-2 focus-visible:outline-(--hola-accent)\",\n    \"[&_svg]:pointer-events-none [&_svg]:shrink-0 [&_svg:not([class*='size-'])]:size-3\"\n  ),\n  {\n    variants: {\n      variant: {\n        // Solid brand badge — for \"new\", \"pro\", primary labels\n        default: cn(\n          \"bg-(--hola-brand) text-(--hola-brand-fg)\",\n          \"[a&]:hover:bg-(--hola-brand)/85\",\n          \"dark:border-(--hola-fg)/5\"\n        ),\n        // Tinted neutral — the workhorse status pill\n        secondary: cn(\n          \"bg-(--hola-fg)/[0.08] text-fg\",\n          \"[a&]:hover:bg-(--hola-fg)/[0.12]\",\n          \"dark:bg-(--hola-fg)/[0.1] dark:[a&]:hover:bg-(--hola-fg)/[0.14]\"\n        ),\n        // Outlined — neutral border, transparent\n        outline: cn(\n          \"border-(--hola-fg)/15 text-fg\",\n          \"[a&]:hover:bg-(--hola-fg)/[0.04]\",\n          \"dark:border-(--hola-fg)/20\"\n        ),\n        // Ghost — bare text, hover background\n        ghost: cn(\n          \"text-fg\",\n          \"[a&]:hover:bg-(--hola-fg)/[0.06]\"\n        ),\n        // Tinted destructive — Linear/Resend style status badge for errors\n        destructive: cn(\n          \"bg-(--hola-danger)/[0.12] text-(--hola-danger)\",\n          \"[a&]:hover:bg-(--hola-danger)/[0.18]\",\n          \"dark:bg-(--hola-danger)/[0.18]\"\n        ),\n        // Link badge — text only with underline on hover\n        link: cn(\n          \"text-(--hola-accent) underline-offset-2\",\n          \"[a&]:hover:underline\"\n        ),\n      },\n    },\n    defaultVariants: {\n      variant: \"default\",\n    },\n  }\n);\n\nfunction Badge({\n  className,\n  variant = \"default\",\n  render,\n  ...props\n}: useRender.ComponentProps<\"span\"> & VariantProps<typeof badgeVariants>) {\n  return useRender({\n    defaultTagName: \"span\",\n    props: mergeProps<\"span\">(\n      { className: cn(badgeVariants({ variant }), className) },\n      props\n    ),\n    render,\n    state: { slot: \"badge\", variant },\n  });\n}\n\nexport { Badge, badgeVariants };\n",
      "type": "registry:ui",
      "target": "components/ui/badge.tsx"
    }
  ],
  "type": "registry:ui"
}